{
   "predictions" : 
   [
      {
         "description" : "Malabon, Metro Manila, Philippines",
         "matched_substrings" : 
         [
            {
               "length" : 3,
               "offset" : 0
            }
         ],
         "place_id" : "ChIJbTDTbGu0lzMRevHRY44dJSA",
         "reference" : "ChIJbTDTbGu0lzMRevHRY44dJSA",
         "structured_formatting" : 
         {
            "main_text" : "Malabon",
            "main_text_matched_substrings" : 
            [
               {
                  "length" : 3,
                  "offset" : 0
               }
            ],
            "secondary_text" : "Metro Manila, Philippines"
         },
         "terms" : 
         [
            {
               "offset" : 0,
               "value" : "Malabon"
            },
            {
               "offset" : 9,
               "value" : "Metro Manila"
            },
            {
               "offset" : 23,
               "value" : "Philippines"
            }
         ],
         "types" : 
         [
            "political",
            "locality",
            "geocode"
         ]
      },
      {
         "description" : "Malolos, Bulacan, Philippines",
         "matched_substrings" : 
         [
            {
               "length" : 3,
               "offset" : 0
            }
         ],
         "place_id" : "ChIJgbh9k69TljMRWT_y11n1sjI",
         "reference" : "ChIJgbh9k69TljMRWT_y11n1sjI",
         "structured_formatting" : 
         {
            "main_text" : "Malolos",
            "main_text_matched_substrings" : 
            [
               {
                  "length" : 3,
                  "offset" : 0
               }
            ],
            "secondary_text" : "Bulacan, Philippines"
         },
         "terms" : 
         [
            {
               "offset" : 0,
               "value" : "Malolos"
            },
            {
               "offset" : 9,
               "value" : "Bulacan"
            },
            {
               "offset" : 18,
               "value" : "Philippines"
            }
         ],
         "types" : 
         [
            "geocode",
            "political",
            "locality"
         ]
      },
      {
         "description" : "Malapascua Island, Daanbantayan, Philippines",
         "matched_substrings" : 
         [
            {
               "length" : 3,
               "offset" : 0
            }
         ],
         "place_id" : "ChIJL4V2qmDepzMRYzMNVDZ4I-k",
         "reference" : "ChIJL4V2qmDepzMRYzMNVDZ4I-k",
         "structured_formatting" : 
         {
            "main_text" : "Malapascua Island",
            "main_text_matched_substrings" : 
            [
               {
                  "length" : 3,
                  "offset" : 0
               }
            ],
            "secondary_text" : "Daanbantayan, Philippines"
         },
         "terms" : 
         [
            {
               "offset" : 0,
               "value" : "Malapascua Island"
            },
            {
               "offset" : 19,
               "value" : "Daanbantayan"
            },
            {
               "offset" : 33,
               "value" : "Philippines"
            }
         ],
         "types" : 
         [
            "establishment",
            "natural_feature"
         ]
      },
      {
         "description" : "Malate, Manila, Metro Manila, Philippines",
         "matched_substrings" : 
         [
            {
               "length" : 3,
               "offset" : 0
            }
         ],
         "place_id" : "ChIJHwpokyrKlzMRhU-mRz5cIcc",
         "reference" : "ChIJHwpokyrKlzMRhU-mRz5cIcc",
         "structured_formatting" : 
         {
            "main_text" : "Malate",
            "main_text_matched_substrings" : 
            [
               {
                  "length" : 3,
                  "offset" : 0
               }
            ],
            "secondary_text" : "Manila, Metro Manila, Philippines"
         },
         "terms" : 
         [
            {
               "offset" : 0,
               "value" : "Malate"
            },
            {
               "offset" : 8,
               "value" : "Manila"
            },
            {
               "offset" : 16,
               "value" : "Metro Manila"
            },
            {
               "offset" : 30,
               "value" : "Philippines"
            }
         ],
         "types" : 
         [
            "sublocality_level_1",
            "political",
            "geocode",
            "sublocality"
         ]
      },
      {
         "description" : "Malico, San Nicolas, Pangasinan, Philippines",
         "matched_substrings" : 
         [
            {
               "length" : 3,
               "offset" : 0
            }
         ],
         "place_id" : "ChIJ1XM_HzQDkTMRdQyAZdS_rjo",
         "reference" : "ChIJ1XM_HzQDkTMRdQyAZdS_rjo",
         "structured_formatting" : 
         {
            "main_text" : "Malico",
            "main_text_matched_substrings" : 
            [
               {
                  "length" : 3,
                  "offset" : 0
               }
            ],
            "secondary_text" : "San Nicolas, Pangasinan, Philippines"
         },
         "terms" : 
         [
            {
               "offset" : 0,
               "value" : "Malico"
            },
            {
               "offset" : 8,
               "value" : "San Nicolas"
            },
            {
               "offset" : 21,
               "value" : "Pangasinan"
            },
            {
               "offset" : 33,
               "value" : "Philippines"
            }
         ],
         "types" : 
         [
            "geocode",
            "sublocality_level_2",
            "sublocality",
            "political"
         ]
      }
   ],
   "status" : "OK"
}