{
   "destination_addresses" : 
   [
      "Quezon Memorial Circle, Elliptical Rd, Diliman, Quezon City, Metro Manila, Philippines",
      "295-B, Purok 4, M. L. Quezon Ave, Lower Bicutan, Taguig, 1632 Metro Manila, Philippines",
      "Quirino Hwy, Philippines"
   ],
   "origin_addresses" : 
   [
      "Quirino Hwy, Philippines",
      "Quezon Memorial Circle, Elliptical Rd, Diliman, Quezon City, Metro Manila, Philippines",
      "295-B, Purok 4, M. L. Quezon Ave, Lower Bicutan, Taguig, 1632 Metro Manila, Philippines"
   ],
   "rows" : 
   [
      {
         "elements" : 
         [
            {
               "distance" : 
               {
                  "text" : "23.8 km",
                  "value" : 23848
               },
               "duration" : 
               {
                  "text" : "57 mins",
                  "value" : 3391
               },
               "status" : "OK"
            },
            {
               "distance" : 
               {
                  "text" : "60.3 km",
                  "value" : 60325
               },
               "duration" : 
               {
                  "text" : "1 hour 40 mins",
                  "value" : 6020
               },
               "status" : "OK"
            },
            {
               "distance" : 
               {
                  "text" : "1 m",
                  "value" : 0
               },
               "duration" : 
               {
                  "text" : "1 min",
                  "value" : 0
               },
               "status" : "OK"
            }
         ]
      },
      {
         "elements" : 
         [
            {
               "distance" : 
               {
                  "text" : "1 m",
                  "value" : 0
               },
               "duration" : 
               {
                  "text" : "1 min",
                  "value" : 0
               },
               "status" : "OK"
            },
            {
               "distance" : 
               {
                  "text" : "27.0 km",
                  "value" : 27010
               },
               "duration" : 
               {
                  "text" : "47 mins",
                  "value" : 2813
               },
               "status" : "OK"
            },
            {
               "distance" : 
               {
                  "text" : "23.5 km",
                  "value" : 23476
               },
               "duration" : 
               {
                  "text" : "55 mins",
                  "value" : 3271
               },
               "status" : "OK"
            }
         ]
      },
      {
         "elements" : 
         [
            {
               "distance" : 
               {
                  "text" : "24.0 km",
                  "value" : 24006
               },
               "duration" : 
               {
                  "text" : "51 mins",
                  "value" : 3049
               },
               "status" : "OK"
            },
            {
               "distance" : 
               {
                  "text" : "1 m",
                  "value" : 0
               },
               "duration" : 
               {
                  "text" : "1 min",
                  "value" : 0
               },
               "status" : "OK"
            },
            {
               "distance" : 
               {
                  "text" : "46.7 km",
                  "value" : 46696
               },
               "duration" : 
               {
                  "text" : "1 hour 39 mins",
                  "value" : 5934
               },
               "status" : "OK"
            }
         ]
      }
   ],
   "status" : "OK"
}