{
   "destination_addresses" : 
   [
      "1339 Angono, Makati, Metro Manila, Philippines",
      "GXPJ+4MV, Seaside Blvd, 123, Pasay, 1300 Metro Manila, Philippines"
   ],
   "origin_addresses" : 
   [
      "GXPJ+4MV, Seaside Blvd, 123, Pasay, 1300 Metro Manila, Philippines",
      "1339 Angono, Makati, Metro Manila, Philippines"
   ],
   "rows" : 
   [
      {
         "elements" : 
         [
            {
               "distance" : 
               {
                  "text" : "7.8 km",
                  "value" : 7850
               },
               "duration" : 
               {
                  "text" : "28 mins",
                  "value" : 1692
               },
               "status" : "OK"
            },
            {
               "distance" : 
               {
                  "text" : "1 m",
                  "value" : 0
               },
               "duration" : 
               {
                  "text" : "1 min",
                  "value" : 0
               },
               "status" : "OK"
            }
         ]
      },
      {
         "elements" : 
         [
            {
               "distance" : 
               {
                  "text" : "1 m",
                  "value" : 0
               },
               "duration" : 
               {
                  "text" : "1 min",
                  "value" : 0
               },
               "status" : "OK"
            },
            {
               "distance" : 
               {
                  "text" : "8.4 km",
                  "value" : 8445
               },
               "duration" : 
               {
                  "text" : "28 mins",
                  "value" : 1689
               },
               "status" : "OK"
            }
         ]
      }
   ],
   "status" : "OK"
}