{
   "destination_addresses" : 
   [
      "7498 b berong st, Maligaya park camarin, Caloocan, Metro Manila, Philippines",
      "P3R8+Q2H, Quezon City, Metro Manila, Philippines"
   ],
   "origin_addresses" : 
   [
      "P3R8+Q2H, Quezon City, Metro Manila, Philippines",
      "7498 b berong st, Maligaya park camarin, Caloocan, Metro Manila, Philippines"
   ],
   "rows" : 
   [
      {
         "elements" : 
         [
            {
               "distance" : 
               {
                  "text" : "0.6 km",
                  "value" : 589
               },
               "duration" : 
               {
                  "text" : "3 mins",
                  "value" : 165
               },
               "status" : "OK"
            },
            {
               "distance" : 
               {
                  "text" : "1 m",
                  "value" : 0
               },
               "duration" : 
               {
                  "text" : "1 min",
                  "value" : 0
               },
               "status" : "OK"
            }
         ]
      },
      {
         "elements" : 
         [
            {
               "distance" : 
               {
                  "text" : "1 m",
                  "value" : 0
               },
               "duration" : 
               {
                  "text" : "1 min",
                  "value" : 0
               },
               "status" : "OK"
            },
            {
               "distance" : 
               {
                  "text" : "0.6 km",
                  "value" : 589
               },
               "duration" : 
               {
                  "text" : "3 mins",
                  "value" : 157
               },
               "status" : "OK"
            }
         ]
      }
   ],
   "status" : "OK"
}