{
   "destination_addresses" : 
   [
      "910 Plaza Miranda, Quiapo, Manila, 1001 Metro Manila, Philippines",
      "Quirino Highway, Barangay corner, Maligaya St, Novaliches, Quezon City, 1118 Metro Manila, Philippines"
   ],
   "origin_addresses" : 
   [
      "Quirino Highway, Barangay corner, Maligaya St, Novaliches, Quezon City, 1118 Metro Manila, Philippines",
      "910 Plaza Miranda, Quiapo, Manila, 1001 Metro Manila, Philippines"
   ],
   "rows" : 
   [
      {
         "elements" : 
         [
            {
               "distance" : 
               {
                  "text" : "27.4 km",
                  "value" : 27355
               },
               "duration" : 
               {
                  "text" : "51 mins",
                  "value" : 3039
               },
               "status" : "OK"
            },
            {
               "distance" : 
               {
                  "text" : "1 m",
                  "value" : 0
               },
               "duration" : 
               {
                  "text" : "1 min",
                  "value" : 0
               },
               "status" : "OK"
            }
         ]
      },
      {
         "elements" : 
         [
            {
               "distance" : 
               {
                  "text" : "1 m",
                  "value" : 0
               },
               "duration" : 
               {
                  "text" : "1 min",
                  "value" : 0
               },
               "status" : "OK"
            },
            {
               "distance" : 
               {
                  "text" : "23.8 km",
                  "value" : 23840
               },
               "duration" : 
               {
                  "text" : "54 mins",
                  "value" : 3248
               },
               "status" : "OK"
            }
         ]
      }
   ],
   "status" : "OK"
}