{
   "destination_addresses" : 
   [
      "Malaria Rd, Caloocan, Metro Manila, Philippines",
      "10 MacArthur Hwy, Malolos, Bulacan, Philippines",
      "Maligaya St, Quezon City, Metro Manila, Philippines"
   ],
   "origin_addresses" : 
   [
      "Maligaya St, Quezon City, Metro Manila, Philippines",
      "Malaria Rd, Caloocan, Metro Manila, Philippines",
      "10 MacArthur Hwy, Malolos, Bulacan, Philippines"
   ],
   "rows" : 
   [
      {
         "elements" : 
         [
            {
               "distance" : 
               {
                  "text" : "6.1 km",
                  "value" : 6082
               },
               "duration" : 
               {
                  "text" : "21 mins",
                  "value" : 1246
               },
               "status" : "OK"
            },
            {
               "distance" : 
               {
                  "text" : "37.1 km",
                  "value" : 37122
               },
               "duration" : 
               {
                  "text" : "1 hour 7 mins",
                  "value" : 4000
               },
               "status" : "OK"
            },
            {
               "distance" : 
               {
                  "text" : "1 m",
                  "value" : 0
               },
               "duration" : 
               {
                  "text" : "1 min",
                  "value" : 0
               },
               "status" : "OK"
            }
         ]
      },
      {
         "elements" : 
         [
            {
               "distance" : 
               {
                  "text" : "1 m",
                  "value" : 0
               },
               "duration" : 
               {
                  "text" : "1 min",
                  "value" : 0
               },
               "status" : "OK"
            },
            {
               "distance" : 
               {
                  "text" : "35.2 km",
                  "value" : 35201
               },
               "duration" : 
               {
                  "text" : "1 hour 16 mins",
                  "value" : 4581
               },
               "status" : "OK"
            },
            {
               "distance" : 
               {
                  "text" : "6.7 km",
                  "value" : 6720
               },
               "duration" : 
               {
                  "text" : "20 mins",
                  "value" : 1224
               },
               "status" : "OK"
            }
         ]
      },
      {
         "elements" : 
         [
            {
               "distance" : 
               {
                  "text" : "34.9 km",
                  "value" : 34919
               },
               "duration" : 
               {
                  "text" : "1 hour 17 mins",
                  "value" : 4635
               },
               "status" : "OK"
            },
            {
               "distance" : 
               {
                  "text" : "1 m",
                  "value" : 0
               },
               "duration" : 
               {
                  "text" : "1 min",
                  "value" : 0
               },
               "status" : "OK"
            },
            {
               "distance" : 
               {
                  "text" : "38.6 km",
                  "value" : 38613
               },
               "duration" : 
               {
                  "text" : "1 hour 12 mins",
                  "value" : 4321
               },
               "status" : "OK"
            }
         ]
      }
   ],
   "status" : "OK"
}